{
  "skill_name": "Regression Analysis",
  "discovery_timestamp": 1760820657.4671218,
  "total_books": 25,
  "books": [
    {
      "title": "Regression Basics, 3rd Edition",
      "id": "https://www.safaribooksonline.com/api/v1/book/9781040124703/",
      "url": "https://learning.oreilly.com/api/v1/book/9781040124703/",
      "isbn": "9781040124703",
      "format": "book"
    },
    {
      "title": "State-Owned Enterprise's Ownership Reform",
      "id": "https://www.safaribooksonline.com/api/v1/book/9781000825770/",
      "url": "https://learning.oreilly.com/api/v1/book/9781000825770/",
      "isbn": "9781000825770",
      "format": "book"
    },
    {
      "title": "Applied Regression Modeling, 3rd Edition",
      "id": "https://www.safaribooksonline.com/api/v1/book/9781119615866/",
      "url": "https://learning.oreilly.com/api/v1/book/9781119615866/",
      "isbn": "9781119615866",
      "format": "book"
    },
    {
      "title": "Quantile Regression",
      "id": "https://www.safaribooksonline.com/api/v1/book/9781119715177/",
      "url": "https://learning.oreilly.com/api/v1/book/9781119715177/",
      "isbn": "9781119715177",
      "format": "book"
    },
    {
      "title": "Regression Analysis with R",
      "id": "https://www.safaribooksonline.com/api/v1/book/9781788627306/",
      "url": "https://learning.oreilly.com/api/v1/book/9781788627306/",
      "isbn": "9781788627306",
      "format": "book"
    },
    {
      "title": "Regression Analysis with Python",
      "id": "https://www.safaribooksonline.com/api/v1/book/9781785286315/",
      "url": "https://learning.oreilly.com/api/v1/book/9781785286315/",
      "isbn": "9781785286315",
      "format": "book"
    },
    {
      "title": "Robust Nonlinear Regression",
      "id": "https://www.safaribooksonline.com/api/v1/book/9781118738061/",
      "url": "https://learning.oreilly.com/api/v1/book/9781118738061/",
      "isbn": "9781118738061",
      "format": "book"
    },
    {
      "title": "Theory of Ridge Regression Estimation with Applications",
      "id": "https://www.safaribooksonline.com/api/v1/book/9781118644614/",
      "url": "https://learning.oreilly.com/api/v1/book/9781118644614/",
      "isbn": "9781118644614",
      "format": "book"
    },
    {
      "title": "Best Fit Lines & Curves",
      "id": "https://www.safaribooksonline.com/api/v1/book/9781351661430/",
      "url": "https://learning.oreilly.com/api/v1/book/9781351661430/",
      "isbn": "9781351661447",
      "format": "book"
    },
    {
      "title": "Nonlinear Systems Stability Analysis",
      "id": "https://www.safaribooksonline.com/api/v1/book/9781466569294/",
      "url": "https://learning.oreilly.com/api/v1/book/9781466569294/",
      "isbn": "9781466569294",
      "format": "book"
    },
    {
      "title": "Regression Analysis Microsoft® Excel®",
      "id": "https://www.safaribooksonline.com/api/v1/book/9780134393537/",
      "url": "https://learning.oreilly.com/api/v1/book/9780134393537/",
      "isbn": "9780134393537",
      "format": "book"
    },
    {
      "title": "Sparse Optimization Theory and Methods",
      "id": "https://www.safaribooksonline.com/api/v1/book/9781351624145/",
      "url": "https://learning.oreilly.com/api/v1/book/9781351624145/",
      "isbn": "9781351624145",
      "format": "book"
    },
    {
      "title": "Constrained Principal Component Analysis and Related Techniques",
      "id": "https://www.safaribooksonline.com/api/v1/book/9781466556683/",
      "url": "https://learning.oreilly.com/api/v1/book/9781466556683/",
      "isbn": "9781466556683",
      "format": "book"
    },
    {
      "title": "Regression for Economics, Second Edition",
      "id": "https://www.safaribooksonline.com/api/v1/book/9781631574443/",
      "url": "https://learning.oreilly.com/api/v1/book/9781631574443/",
      "isbn": "9781631574443",
      "format": "book"
    },
    {
      "title": "Logistic Regression Using SAS, 2nd Edition",
      "id": "https://www.safaribooksonline.com/api/v1/book/9781607649953/",
      "url": "https://learning.oreilly.com/api/v1/book/9781607649953/",
      "isbn": "9781607649953",
      "format": "book"
    },
    {
      "title": "Fixed Effects Regression Methods for Longitudinal Data Using SAS",
      "id": "https://www.safaribooksonline.com/api/v1/book/9781590475683/",
      "url": "https://learning.oreilly.com/api/v1/book/9781590475683/",
      "isbn": "9781590475683",
      "format": "book"
    },
    {
      "title": "Regression Analysis",
      "id": "https://www.safaribooksonline.com/api/v1/book/9781631573866/",
      "url": "https://learning.oreilly.com/api/v1/book/9781631573866/",
      "isbn": "9781631573866",
      "format": "book"
    },
    {
      "title": "Business Applications of Multiple Regression, Second Edition",
      "id": "https://www.safaribooksonline.com/api/v1/book/9781631570599/",
      "url": "https://learning.oreilly.com/api/v1/book/9781631570599/",
      "isbn": "9781631570605",
      "format": "book"
    },
    {
      "title": "Advanced Backend Optimization",
      "id": "https://www.safaribooksonline.com/api/v1/book/9781118648957/",
      "url": "https://learning.oreilly.com/api/v1/book/9781118648957/",
      "isbn": "9781118648957",
      "format": "book"
    },
    {
      "title": "American-Type Options",
      "id": "https://www.safaribooksonline.com/api/v1/book/9783110329681/",
      "url": "https://learning.oreilly.com/api/v1/book/9783110329681/",
      "isbn": "9783110389906",
      "format": "book"
    },
    {
      "title": "Applied Survival Analysis: Regression Modeling of Time to Event Data, 2nd Edition",
      "id": "https://www.safaribooksonline.com/api/v1/book/9781118211588/",
      "url": "https://learning.oreilly.com/api/v1/book/9781118211588/",
      "isbn": "9781118211588",
      "format": "book"
    },
    {
      "title": "Regression for Economics",
      "id": "https://www.safaribooksonline.com/api/v1/book/9781606494059/",
      "url": "https://learning.oreilly.com/api/v1/book/9781606494059/",
      "isbn": "9781606494066",
      "format": "book"
    },
    {
      "title": "Regression Analysis",
      "id": "https://www.safaribooksonline.com/api/v1/book/9781606494349/",
      "url": "https://learning.oreilly.com/api/v1/book/9781606494349/",
      "isbn": "9781606494356",
      "format": "book"
    },
    {
      "title": "Dose Finding by the Continual Reassessment Method",
      "id": "https://www.safaribooksonline.com/api/v1/book/9781420091526/",
      "url": "https://learning.oreilly.com/api/v1/book/9781420091526/",
      "isbn": "9781420091526",
      "format": "book"
    },
    {
      "title": "Regression Analysis by Example, 4th Edition",
      "id": "https://www.safaribooksonline.com/api/v1/book/9780471746966/",
      "url": "https://learning.oreilly.com/api/v1/book/9780471746966/",
      "isbn": "9780471746966",
      "format": "book"
    }
  ]
}