{
  "skill_name": "Data Engineering",
  "discovery_timestamp": "2025-10-19 17:15:24",
  "total_books": 118,
  "books": [
    {
      "title": "Designing Data-Intensive Applications, 2nd Edition",
      "id": "https://www.safaribooksonline.com/api/v1/book/9781098119058/",
      "url": "https://learning.oreilly.com/api/v1/book/9781098119058/",
      "isbn": "9781098119065",
      "format": "book",
      "main_topic": "Data Engineering",
      "secondary_topics": []
    },
    {
      "title": "Fundamentals of Data Engineering",
      "id": "https://www.safaribooksonline.com/api/v1/book/9781098108298/",
      "url": "https://learning.oreilly.com/api/v1/book/9781098108298/",
      "isbn": "9781098108304",
      "format": "book",
      "main_topic": "Data Engineering",
      "secondary_topics": []
    },
    {
      "title": "Designing Data-Intensive Applications",
      "id": "https://www.safaribooksonline.com/api/v1/book/9781491903063/",
      "url": "https://learning.oreilly.com/api/v1/book/9781491903063/",
      "isbn": "9781491903100",
      "format": "book",
      "main_topic": "Data Engineering",
      "secondary_topics": []
    },
    {
      "title": "Data Engineering Design Patterns",
      "id": "https://www.safaribooksonline.com/api/v1/book/9781098165826/",
      "url": "https://learning.oreilly.com/api/v1/book/9781098165826/",
      "isbn": "9781098165819",
      "format": "book",
      "main_topic": "Data Engineering",
      "secondary_topics": []
    },
    {
      "title": "Financial Data Engineering",
      "id": "https://www.safaribooksonline.com/api/v1/book/9781098159986/",
      "url": "https://learning.oreilly.com/api/v1/book/9781098159986/",
      "isbn": "9781098159993",
      "format": "book",
      "main_topic": "Data Engineering",
      "secondary_topics": []
    },
    {
      "title": "Data Engineering Best Practices",
      "id": "https://www.safaribooksonline.com/api/v1/book/9781803244983/",
      "url": "https://learning.oreilly.com/api/v1/book/9781803244983/",
      "isbn": "9781803244983",
      "format": "book",
      "main_topic": "Data Engineering",
      "secondary_topics": []
    },
    {
      "title": "Managing Data as a Product",
      "id": "https://www.safaribooksonline.com/api/v1/book/9781835468531/",
      "url": "https://learning.oreilly.com/api/v1/book/9781835468531/",
      "isbn": "9781835468531",
      "format": "book",
      "main_topic": "Data Engineering",
      "secondary_topics": []
    },
    {
      "title": "Data Engineering with dbt",
      "id": "https://www.safaribooksonline.com/api/v1/book/9781803246284/",
      "url": "https://learning.oreilly.com/api/v1/book/9781803246284/",
      "isbn": "9781803246284",
      "format": "book",
      "main_topic": "Data Engineering",
      "secondary_topics": []
    },
    {
      "title": "Data Engineering with AWS - Second Edition",
      "id": "https://www.safaribooksonline.com/api/v1/book/9781804614426/",
      "url": "https://learning.oreilly.com/api/v1/book/9781804614426/",
      "isbn": "9781804614426",
      "format": "book",
      "main_topic": "Data Engineering",
      "secondary_topics": []
    },
    {
      "title": "Data Engineering with Databricks Cookbook",
      "id": "https://www.safaribooksonline.com/api/v1/book/9781837633357/",
      "url": "https://learning.oreilly.com/api/v1/book/9781837633357/",
      "isbn": "9781837633357",
      "format": "book",
      "main_topic": "Data Engineering",
      "secondary_topics": []
    },
    {
      "title": "The Definitive Guide to Data Integration",
      "id": "https://www.safaribooksonline.com/api/v1/book/9781837631919/",
      "url": "https://learning.oreilly.com/api/v1/book/9781837631919/",
      "isbn": "9781837631919",
      "format": "book",
      "main_topic": "Data Engineering",
      "secondary_topics": []
    },
    {
      "title": "Data Engineering with AWS Cookbook",
      "id": "https://www.safaribooksonline.com/api/v1/book/9781805127284/",
      "url": "https://learning.oreilly.com/api/v1/book/9781805127284/",
      "isbn": "9781805127284",
      "format": "book",
      "main_topic": "Data Engineering",
      "secondary_topics": []
    },
    {
      "title": "Cracking the Data Engineering Interview",
      "id": "https://www.safaribooksonline.com/api/v1/book/9781837630776/",
      "url": "https://learning.oreilly.com/api/v1/book/9781837630776/",
      "isbn": "9781837630776",
      "format": "book",
      "main_topic": "Data Engineering",
      "secondary_topics": []
    },
    {
      "title": "Unlock Data Agility with Composable Data Architecture",
      "id": "https://www.safaribooksonline.com/api/v1/book/9781098178956/",
      "url": "https://learning.oreilly.com/api/v1/book/9781098178956/",
      "isbn": "9781098178949",
      "format": "book",
      "main_topic": "Data Engineering",
      "secondary_topics": []
    },
    {
      "title": "Data Observability for Data Engineering",
      "id": "https://www.safaribooksonline.com/api/v1/book/9781804616024/",
      "url": "https://learning.oreilly.com/api/v1/book/9781804616024/",
      "isbn": "9781804616024",
      "format": "book",
      "main_topic": "Data Engineering",
      "secondary_topics": []
    },
    {
      "title": "Accelerating Data Pipeline Development",
      "id": "https://www.safaribooksonline.com/api/v1/book/9798341608757/",
      "url": "https://learning.oreilly.com/api/v1/book/9798341608757/",
      "isbn": "9798341608764",
      "format": "book",
      "main_topic": "Data Engineering",
      "secondary_topics": []
    },
    {
      "title": "Data Pipelines Pocket Reference",
      "id": "https://www.safaribooksonline.com/api/v1/book/9781492087823/",
      "url": "https://learning.oreilly.com/api/v1/book/9781492087823/",
      "isbn": "9781492087830",
      "format": "book",
      "main_topic": "Data Engineering",
      "secondary_topics": []
    },
    {
      "title": "Data Security Blueprints",
      "id": "https://www.safaribooksonline.com/api/v1/book/9781098172985/",
      "url": "https://learning.oreilly.com/api/v1/book/9781098172985/",
      "isbn": "9781098172978",
      "format": "book",
      "main_topic": "Data Engineering",
      "secondary_topics": []
    },
    {
      "title": "Data Engineering with Python",
      "id": "https://www.safaribooksonline.com/api/v1/book/9781839214189/",
      "url": "https://learning.oreilly.com/api/v1/book/9781839214189/",
      "isbn": "9781839214189",
      "format": "book",
      "main_topic": "Data Engineering",
      "secondary_topics": []
    },
    {
      "title": "Azure Data Engineering Cookbook - Second Edition",
      "id": "https://www.safaribooksonline.com/api/v1/book/9781803246789/",
      "url": "https://learning.oreilly.com/api/v1/book/9781803246789/",
      "isbn": "9781803246789",
      "format": "book",
      "main_topic": "Data Engineering",
      "secondary_topics": []
    },
    {
      "title": "Simplifying Data Engineering and Analytics with Delta",
      "id": "https://www.safaribooksonline.com/api/v1/book/9781801814867/",
      "url": "https://learning.oreilly.com/api/v1/book/9781801814867/",
      "isbn": "9781801814867",
      "format": "book",
      "main_topic": "Data Engineering",
      "secondary_topics": []
    },
    {
      "title": "Cost-Effective Data Pipelines",
      "id": "https://www.safaribooksonline.com/api/v1/book/9781492098638/",
      "url": "https://learning.oreilly.com/api/v1/book/9781492098638/",
      "isbn": "9781492098645",
      "format": "book",
      "main_topic": "Data Engineering",
      "secondary_topics": []
    },
    {
      "title": "97 Things Every Data Engineer Should Know",
      "id": "https://www.safaribooksonline.com/api/v1/book/9781492062400/",
      "url": "https://learning.oreilly.com/api/v1/book/9781492062400/",
      "isbn": "9781492062417",
      "format": "book",
      "main_topic": "Data Engineering",
      "secondary_topics": []
    },
    {
      "title": "Data Engineering on Azure",
      "id": "https://www.safaribooksonline.com/api/v1/book/9781617298929/",
      "url": "https://learning.oreilly.com/api/v1/book/9781617298929/",
      "isbn": "9781617298929",
      "format": "book",
      "main_topic": "Data Engineering",
      "secondary_topics": []
    },
    {
      "title": "Data Engineering with AWS",
      "id": "https://www.safaribooksonline.com/api/v1/book/9781800560413/",
      "url": "https://learning.oreilly.com/api/v1/book/9781800560413/",
      "isbn": "9781800560413",
      "format": "book",
      "main_topic": "Data Engineering",
      "secondary_topics": []
    },
    {
      "title": "Designing Big Data Platforms",
      "id": "https://www.safaribooksonline.com/api/v1/book/9781119690924/",
      "url": "https://learning.oreilly.com/api/v1/book/9781119690924/",
      "isbn": "9781119690924",
      "format": "book",
      "main_topic": "Data Engineering",
      "secondary_topics": []
    },
    {
      "title": "High-Performance Data Architectures",
      "id": "https://www.safaribooksonline.com/api/v1/book/9781098150556/",
      "url": "https://learning.oreilly.com/api/v1/book/9781098150556/",
      "isbn": "9781098150549",
      "format": "book",
      "main_topic": "Data Engineering",
      "secondary_topics": []
    },
    {
      "title": "Building Data Products",
      "id": "https://www.safaribooksonline.com/api/v1/book/9798341629394/",
      "url": "https://learning.oreilly.com/api/v1/book/9798341629394/",
      "isbn": "9798341629400",
      "format": "book",
      "main_topic": "Data Engineering",
      "secondary_topics": []
    },
    {
      "title": "Big Data Management",
      "id": "https://www.safaribooksonline.com/api/v1/book/9783110664324/",
      "url": "https://learning.oreilly.com/api/v1/book/9783110664324/",
      "isbn": "9783110664324",
      "format": "book",
      "main_topic": "Data Engineering",
      "secondary_topics": []
    },
    {
      "title": "Data Engineering for Multimodal AI",
      "id": "https://www.safaribooksonline.com/api/v1/book/9781098190774/",
      "url": "https://learning.oreilly.com/api/v1/book/9781098190774/",
      "isbn": "9781098190781",
      "format": "book",
      "main_topic": "Data Engineering",
      "secondary_topics": []
    },
    {
      "title": "Data Engineering with Alteryx",
      "id": "https://www.safaribooksonline.com/api/v1/book/9781803236483/",
      "url": "https://learning.oreilly.com/api/v1/book/9781803236483/",
      "isbn": "9781803236483",
      "format": "book",
      "main_topic": "Data Engineering",
      "secondary_topics": []
    },
    {
      "title": "Supervised and Unsupervised Data Engineering for Multimedia Data",
      "id": "https://www.safaribooksonline.com/api/v1/book/9781119786344/",
      "url": "https://learning.oreilly.com/api/v1/book/9781119786344/",
      "isbn": "9781119786344",
      "format": "book",
      "main_topic": "Data Engineering",
      "secondary_topics": []
    },
    {
      "title": "Modern Big Data Architectures",
      "id": "https://www.safaribooksonline.com/api/v1/book/9781119597841/",
      "url": "https://learning.oreilly.com/api/v1/book/9781119597841/",
      "isbn": "9781119597841",
      "format": "book",
      "main_topic": "Data Engineering",
      "secondary_topics": []
    },
    {
      "title": "Data Contracts in Practice",
      "id": "https://www.safaribooksonline.com/api/v1/book/9781836209157/",
      "url": "https://learning.oreilly.com/api/v1/book/9781836209157/",
      "isbn": "9781836209157",
      "format": "book",
      "main_topic": "Data Engineering",
      "secondary_topics": []
    },
    {
      "title": "Data Architecture: A Primer for the Data Scientist, 2nd Edition",
      "id": "https://www.safaribooksonline.com/api/v1/book/9780128169179/",
      "url": "https://learning.oreilly.com/api/v1/book/9780128169179/",
      "isbn": "9780128169179",
      "format": "book",
      "main_topic": "Data Engineering",
      "secondary_topics": []
    },
    {
      "title": "Data Fabric as Modern Data Architecture",
      "id": "https://www.safaribooksonline.com/api/v1/book/9781098105952/",
      "url": "https://learning.oreilly.com/api/v1/book/9781098105952/",
      "isbn": "9781098105945",
      "format": "book",
      "main_topic": "Data Engineering",
      "secondary_topics": []
    },
    {
      "title": "Automating Data Transformations",
      "id": "https://www.safaribooksonline.com/api/v1/book/9781098147594/",
      "url": "https://learning.oreilly.com/api/v1/book/9781098147594/",
      "isbn": "9781098147587",
      "format": "book",
      "main_topic": "Data Engineering",
      "secondary_topics": []
    },
    {
      "title": "The Rise of the Knowledge Graph",
      "id": "https://www.safaribooksonline.com/api/v1/book/9781098100407/",
      "url": "https://learning.oreilly.com/api/v1/book/9781098100407/",
      "isbn": "9781098100391",
      "format": "book",
      "main_topic": "Data Engineering",
      "secondary_topics": []
    },
    {
      "title": "Data Engineering for Cybersecurity",
      "id": "https://www.safaribooksonline.com/api/v1/book/0642572230111/",
      "url": "https://learning.oreilly.com/api/v1/book/0642572230111/",
      "isbn": "9781718504028",
      "format": "book",
      "main_topic": "Data Engineering",
      "secondary_topics": []
    },
    {
      "title": "Azure Data Engineering Cookbook",
      "id": "https://www.safaribooksonline.com/api/v1/book/9781800206557/",
      "url": "https://learning.oreilly.com/api/v1/book/9781800206557/",
      "isbn": "9781800206557",
      "format": "book",
      "main_topic": "Data Engineering",
      "secondary_topics": []
    },
    {
      "title": "Foundations of Data Intensive Applications",
      "id": "https://www.safaribooksonline.com/api/v1/book/9781119713029/",
      "url": "https://learning.oreilly.com/api/v1/book/9781119713029/",
      "isbn": "9781119713029",
      "format": "book",
      "main_topic": "Data Engineering",
      "secondary_topics": []
    },
    {
      "title": "Data Usability in the Enterprise: How Usability Leads to Optimal Digital Experiences",
      "id": "https://www.safaribooksonline.com/api/v1/book/9798868811838/",
      "url": "https://learning.oreilly.com/api/v1/book/9798868811838/",
      "isbn": "9798868811838",
      "format": "book",
      "main_topic": "Data Engineering",
      "secondary_topics": []
    },
    {
      "title": "The Unrealized Opportunities with Real-Time Data",
      "id": "https://www.safaribooksonline.com/api/v1/book/9781098145125/",
      "url": "https://learning.oreilly.com/api/v1/book/9781098145125/",
      "isbn": "9781098145118",
      "format": "book",
      "main_topic": "Data Engineering",
      "secondary_topics": []
    },
    {
      "title": "Building a Fast Universal Data Access Platform",
      "id": "https://www.safaribooksonline.com/api/v1/book/9781098155353/",
      "url": "https://learning.oreilly.com/api/v1/book/9781098155353/",
      "isbn": "9781098155346",
      "format": "book",
      "main_topic": "Data Engineering",
      "secondary_topics": []
    },
    {
      "title": "Why External Data Needs to Be Part of Your Data and Analytics Strategy",
      "id": "https://www.safaribooksonline.com/api/v1/book/9781098120139/",
      "url": "https://learning.oreilly.com/api/v1/book/9781098120139/",
      "isbn": "9781098120122",
      "format": "book",
      "main_topic": "Data Engineering",
      "secondary_topics": []
    },
    {
      "title": "What Is Data Engineering?",
      "id": "https://www.safaribooksonline.com/api/v1/book/9781492075578/",
      "url": "https://learning.oreilly.com/api/v1/book/9781492075578/",
      "isbn": "9781492075561",
      "format": "book",
      "main_topic": "Data Engineering",
      "secondary_topics": []
    },
    {
      "title": "Mastering Large Datasets with Python",
      "id": "https://www.safaribooksonline.com/api/v1/book/9781617296239/",
      "url": "https://learning.oreilly.com/api/v1/book/9781617296239/",
      "isbn": "9781617296239",
      "format": "book",
      "main_topic": "Data Engineering",
      "secondary_topics": []
    },
    {
      "title": "Big Data",
      "id": "https://www.safaribooksonline.com/api/v1/book/9781617290343/",
      "url": "https://learning.oreilly.com/api/v1/book/9781617290343/",
      "isbn": "9781617290343",
      "format": "book",
      "main_topic": "Data Engineering",
      "secondary_topics": []
    },
    {
      "title": "Architecting Data-Intensive SaaS Applications",
      "id": "https://www.safaribooksonline.com/api/v1/book/9781098102760/",
      "url": "https://learning.oreilly.com/api/v1/book/9781098102760/",
      "isbn": "9781098102753",
      "format": "book",
      "main_topic": "Data Engineering",
      "secondary_topics": []
    },
    {
      "title": "Data Conscience",
      "id": "https://www.safaribooksonline.com/api/v1/book/9781119821182/",
      "url": "https://learning.oreilly.com/api/v1/book/9781119821182/",
      "isbn": "9781119821182",
      "format": "book",
      "main_topic": "Data Engineering",
      "secondary_topics": []
    },
    {
      "title": "The Evolving Role of the Data Engineer",
      "id": "https://www.safaribooksonline.com/api/v1/book/9781492052517/",
      "url": "https://learning.oreilly.com/api/v1/book/9781492052517/",
      "isbn": "9781492052500",
      "format": "book",
      "main_topic": "Data Engineering",
      "secondary_topics": []
    },
    {
      "title": "The Enterprise Big Data Framework",
      "id": "https://www.safaribooksonline.com/api/v1/book/9781398601727/",
      "url": "https://learning.oreilly.com/api/v1/book/9781398601727/",
      "isbn": "9781398601727",
      "format": "book",
      "main_topic": "Data Engineering",
      "secondary_topics": []
    },
    {
      "title": "Rebuilding Reliable Data Pipelines Through Modern Tools",
      "id": "https://www.safaribooksonline.com/api/v1/book/9781492058175/",
      "url": "https://learning.oreilly.com/api/v1/book/9781492058175/",
      "isbn": "9781492058168",
      "format": "book",
      "main_topic": "Data Engineering",
      "secondary_topics": []
    },
    {
      "title": "Getting DataOps Right",
      "id": "https://www.safaribooksonline.com/api/v1/book/9781492031765/",
      "url": "https://learning.oreilly.com/api/v1/book/9781492031765/",
      "isbn": "9781492031758",
      "format": "book",
      "main_topic": "Data Engineering",
      "secondary_topics": []
    },
    {
      "title": "The Rise of Operational Analytics",
      "id": "https://www.safaribooksonline.com/api/v1/book/9781492073697/",
      "url": "https://learning.oreilly.com/api/v1/book/9781492073697/",
      "isbn": "9781492073680",
      "format": "book",
      "main_topic": "Data Engineering",
      "secondary_topics": []
    },
    {
      "title": "Data Accelerator for AI and Analytics",
      "id": "https://www.safaribooksonline.com/api/v1/book/9780738459325/",
      "url": "https://learning.oreilly.com/api/v1/book/9780738459325/",
      "isbn": "9780738459325",
      "format": "book",
      "main_topic": "Data Engineering",
      "secondary_topics": []
    },
    {
      "title": "Next-Generation Big Data: A Practical Guide to Apache Kudu, Impala, and Spark",
      "id": "https://www.safaribooksonline.com/api/v1/book/9781484231470/",
      "url": "https://learning.oreilly.com/api/v1/book/9781484231470/",
      "isbn": "9781484231470",
      "format": "book",
      "main_topic": "Data Engineering",
      "secondary_topics": []
    },
    {
      "title": "Fifty Years of Data Management and Beyond",
      "id": "https://www.safaribooksonline.com/api/v1/book/9781492057512/",
      "url": "https://learning.oreilly.com/api/v1/book/9781492057512/",
      "isbn": "9781492057505",
      "format": "book",
      "main_topic": "Data Engineering",
      "secondary_topics": []
    },
    {
      "title": "Open Source Data Pipelines for Intelligent Applications",
      "id": "https://www.safaribooksonline.com/api/v1/book/9781492074281/",
      "url": "https://learning.oreilly.com/api/v1/book/9781492074281/",
      "isbn": "9781492074274",
      "format": "book",
      "main_topic": "Data Engineering",
      "secondary_topics": []
    },
    {
      "title": "Building a Unified Data Infrastructure",
      "id": "https://www.safaribooksonline.com/api/v1/book/9781492063254/",
      "url": "https://learning.oreilly.com/api/v1/book/9781492063254/",
      "isbn": "9781492063254",
      "format": "book",
      "main_topic": "Data Engineering",
      "secondary_topics": []
    },
    {
      "title": "Data Architecture: A Primer for the Data Scientist",
      "id": "https://www.safaribooksonline.com/api/v1/book/9780128020449/",
      "url": "https://learning.oreilly.com/api/v1/book/9780128020449/",
      "isbn": "9780128020913",
      "format": "book",
      "main_topic": "Data Engineering",
      "secondary_topics": []
    },
    {
      "title": "Big Data in Practice",
      "id": "https://www.safaribooksonline.com/api/v1/book/9781119231387/",
      "url": "https://learning.oreilly.com/api/v1/book/9781119231387/",
      "isbn": "9781119231387",
      "format": "book",
      "main_topic": "Data Engineering",
      "secondary_topics": []
    },
    {
      "title": "Big Data Demystified",
      "id": "https://www.safaribooksonline.com/api/v1/book/9781292218120/",
      "url": "https://learning.oreilly.com/api/v1/book/9781292218120/",
      "isbn": "9781292218120",
      "format": "book",
      "main_topic": "Data Engineering",
      "secondary_topics": []
    },
    {
      "title": "Big Data Now: 2016 Edition",
      "id": "https://www.safaribooksonline.com/api/v1/book/9781492049197/",
      "url": "https://learning.oreilly.com/api/v1/book/9781492049197/",
      "isbn": "9781491977484",
      "format": "book",
      "main_topic": "Data Engineering",
      "secondary_topics": []
    },
    {
      "title": "Scaling Data Services with Pivotal GemFire",
      "id": "https://www.safaribooksonline.com/api/v1/book/9781492027584/",
      "url": "https://learning.oreilly.com/api/v1/book/9781492027584/",
      "isbn": "9781492027584",
      "format": "book",
      "main_topic": "Data Engineering",
      "secondary_topics": []
    },
    {
      "title": "Big Data",
      "id": "https://www.safaribooksonline.com/api/v1/book/9781498734875/",
      "url": "https://learning.oreilly.com/api/v1/book/9781498734875/",
      "isbn": "9781498734875",
      "format": "book",
      "main_topic": "Data Engineering",
      "secondary_topics": []
    },
    {
      "title": "Introduction to GPUs for Data Analytics",
      "id": "https://www.safaribooksonline.com/api/v1/book/9781491998045/",
      "url": "https://learning.oreilly.com/api/v1/book/9781491998045/",
      "isbn": "9781491998045",
      "format": "book",
      "main_topic": "Data Engineering",
      "secondary_topics": []
    },
    {
      "title": "Obtaining Value from Big Data for Service Systems, Volume II, 2nd Edition",
      "id": "https://www.safaribooksonline.com/api/v1/book/9781949991475/",
      "url": "https://learning.oreilly.com/api/v1/book/9781949991475/",
      "isbn": "9781949991475",
      "format": "book",
      "main_topic": "Data Engineering",
      "secondary_topics": []
    },
    {
      "title": "Obtaining Value from Big Data for Service Systems, Volume I, 2nd Edition",
      "id": "https://www.safaribooksonline.com/api/v1/book/9781949443561/",
      "url": "https://learning.oreilly.com/api/v1/book/9781949443561/",
      "isbn": "9781949443561",
      "format": "book",
      "main_topic": "Data Engineering",
      "secondary_topics": []
    },
    {
      "title": "Perspectives on Data Science for Software Engineering",
      "id": "https://www.safaribooksonline.com/api/v1/book/9780128042618/",
      "url": "https://learning.oreilly.com/api/v1/book/9780128042618/",
      "isbn": "9780128042618",
      "format": "book",
      "main_topic": "Data Engineering",
      "secondary_topics": []
    },
    {
      "title": "Big Data",
      "id": "https://www.safaribooksonline.com/api/v1/book/9780128093467/",
      "url": "https://learning.oreilly.com/api/v1/book/9780128093467/",
      "isbn": "9780128093467",
      "format": "book",
      "main_topic": "Data Engineering",
      "secondary_topics": []
    },
    {
      "title": "Getting Started with Hazelcast, Second Edition",
      "id": "https://www.safaribooksonline.com/api/v1/book/9781785285332/",
      "url": "https://learning.oreilly.com/api/v1/book/9781785285332/",
      "isbn": "9781785285332",
      "format": "book",
      "main_topic": "Data Engineering",
      "secondary_topics": []
    },
    {
      "title": "Fundamentals of Database Management Systems, Second Edition",
      "id": "https://www.safaribooksonline.com/api/v1/book/9781118213575/",
      "url": "https://learning.oreilly.com/api/v1/book/9781118213575/",
      "isbn": "9781118213575",
      "format": "book",
      "main_topic": "Data Engineering",
      "secondary_topics": []
    },
    {
      "title": "Introducing database reliability engineering",
      "id": "https://www.safaribooksonline.com/api/v1/book/9781492030843/",
      "url": "https://learning.oreilly.com/api/v1/book/9781492030843/",
      "isbn": "9781492030836",
      "format": "book",
      "main_topic": "Data Engineering",
      "secondary_topics": []
    },
    {
      "title": "Designing Fast Data Application Architectures",
      "id": "https://www.safaribooksonline.com/api/v1/book/9781492038054/",
      "url": "https://learning.oreilly.com/api/v1/book/9781492038054/",
      "isbn": "9781492038054",
      "format": "book",
      "main_topic": "Data Engineering",
      "secondary_topics": []
    },
    {
      "title": "Getting Data Right",
      "id": "https://www.safaribooksonline.com/api/v1/book/9781491935361/",
      "url": "https://learning.oreilly.com/api/v1/book/9781491935361/",
      "isbn": "9781491935361",
      "format": "book",
      "main_topic": "Data Engineering",
      "secondary_topics": []
    },
    {
      "title": "CMDB Systems",
      "id": "https://www.safaribooksonline.com/api/v1/book/9780128012659/",
      "url": "https://learning.oreilly.com/api/v1/book/9780128012659/",
      "isbn": "9780128013731",
      "format": "book",
      "main_topic": "Data Engineering",
      "secondary_topics": []
    },
    {
      "title": "Big Data SMACK: A Guide to Apache Spark, Mesos, Akka, Cassandra, and Kafka",
      "id": "https://www.safaribooksonline.com/api/v1/book/9781484221754/",
      "url": "https://learning.oreilly.com/api/v1/book/9781484221754/",
      "isbn": "9781484221754",
      "format": "book",
      "main_topic": "Data Engineering",
      "secondary_topics": []
    },
    {
      "title": "Advanced Data Management",
      "id": "https://www.safaribooksonline.com/api/v1/book/9783110433074/",
      "url": "https://learning.oreilly.com/api/v1/book/9783110433074/",
      "isbn": "9783110433074",
      "format": "book",
      "main_topic": "Data Engineering",
      "secondary_topics": []
    },
    {
      "title": "Development Workflows for Data Scientists",
      "id": "https://www.safaribooksonline.com/api/v1/book/9781492049319/",
      "url": "https://learning.oreilly.com/api/v1/book/9781492049319/",
      "isbn": "9781491983324",
      "format": "book",
      "main_topic": "Data Engineering",
      "secondary_topics": []
    },
    {
      "title": "Big Data Now: 2015 Edition",
      "id": "https://www.safaribooksonline.com/api/v1/book/9781492042273/",
      "url": "https://learning.oreilly.com/api/v1/book/9781492042273/",
      "isbn": "9781491950579",
      "format": "book",
      "main_topic": "Data Engineering",
      "secondary_topics": []
    },
    {
      "title": "The Big Data Transformation",
      "id": "https://www.safaribooksonline.com/api/v1/book/9781492049012/",
      "url": "https://learning.oreilly.com/api/v1/book/9781492049012/",
      "isbn": "9781491964736",
      "format": "book",
      "main_topic": "Data Engineering",
      "secondary_topics": []
    },
    {
      "title": "The Big Data-Driven Business",
      "id": "https://www.safaribooksonline.com/api/v1/book/9781118889800/",
      "url": "https://learning.oreilly.com/api/v1/book/9781118889800/",
      "isbn": "9781118889800",
      "format": "book",
      "main_topic": "Data Engineering",
      "secondary_topics": []
    },
    {
      "title": "Big Data, Open Data and Data Development",
      "id": "https://www.safaribooksonline.com/api/v1/book/9781848218802/",
      "url": "https://learning.oreilly.com/api/v1/book/9781848218802/",
      "isbn": "9781848218802",
      "format": "book",
      "main_topic": "Data Engineering",
      "secondary_topics": []
    },
    {
      "title": "Data Structure and Software Engineering",
      "id": "https://www.safaribooksonline.com/api/v1/book/9781926692975/",
      "url": "https://learning.oreilly.com/api/v1/book/9781926692975/",
      "isbn": "9781466562608",
      "format": "book",
      "main_topic": "Data Engineering",
      "secondary_topics": []
    },
    {
      "title": "The Global Impact of Open Data",
      "id": "https://www.safaribooksonline.com/api/v1/book/9781492042785/",
      "url": "https://learning.oreilly.com/api/v1/book/9781492042785/",
      "isbn": "9781491964668",
      "format": "book",
      "main_topic": "Data Engineering",
      "secondary_topics": []
    },
    {
      "title": "Architecting for Access",
      "id": "https://www.safaribooksonline.com/api/v1/book/9781492042723/",
      "url": "https://learning.oreilly.com/api/v1/book/9781492042723/",
      "isbn": "9781491960240",
      "format": "book",
      "main_topic": "Data Engineering",
      "secondary_topics": []
    },
    {
      "title": "Data Fluency: Empowering Your Organization with Effective Data Communication",
      "id": "https://www.safaribooksonline.com/api/v1/book/9781118851005/",
      "url": "https://learning.oreilly.com/api/v1/book/9781118851005/",
      "isbn": "9781118851012",
      "format": "book",
      "main_topic": "Data Engineering",
      "secondary_topics": []
    },
    {
      "title": "The Big Data Market",
      "id": "https://www.safaribooksonline.com/api/v1/book/9781492049838/",
      "url": "https://learning.oreilly.com/api/v1/book/9781492049838/",
      "isbn": "9781491959909",
      "format": "book",
      "main_topic": "Data Engineering",
      "secondary_topics": []
    },
    {
      "title": "Big Data",
      "id": "https://www.safaribooksonline.com/api/v1/book/9781118965832/",
      "url": "https://learning.oreilly.com/api/v1/book/9781118965832/",
      "isbn": "9781118965832",
      "format": "book",
      "main_topic": "Data Engineering",
      "secondary_topics": []
    },
    {
      "title": "Dataflow Processing",
      "id": "https://www.safaribooksonline.com/api/v1/book/9780128021347/",
      "url": "https://learning.oreilly.com/api/v1/book/9780128021347/",
      "isbn": "9780128023426",
      "format": "book",
      "main_topic": "Data Engineering",
      "secondary_topics": []
    },
    {
      "title": "Big Data War",
      "id": "https://www.safaribooksonline.com/api/v1/book/9781631575617/",
      "url": "https://learning.oreilly.com/api/v1/book/9781631575617/",
      "isbn": "9781631575617",
      "format": "book",
      "main_topic": "Data Engineering",
      "secondary_topics": []
    },
    {
      "title": "Getting a Big Data Job For Dummies",
      "id": "https://www.safaribooksonline.com/api/v1/book/9781118903841/",
      "url": "https://learning.oreilly.com/api/v1/book/9781118903841/",
      "isbn": "9781118903407",
      "format": "book",
      "main_topic": "Data Engineering",
      "secondary_topics": []
    },
    {
      "title": "Current State of Big Data Use in Retail Supply Chains",
      "id": "https://www.safaribooksonline.com/api/v1/book/9780134136943/",
      "url": "https://learning.oreilly.com/api/v1/book/9780134136943/",
      "isbn": "9780134136943",
      "format": "book",
      "main_topic": "Data Engineering",
      "secondary_topics": []
    },
    {
      "title": "Data Just Right: Introduction to Large-Scale Data & Analytics",
      "id": "https://www.safaribooksonline.com/api/v1/book/9780133359084/",
      "url": "https://learning.oreilly.com/api/v1/book/9780133359084/",
      "isbn": "9780133359084",
      "format": "book",
      "main_topic": "Data Engineering",
      "secondary_topics": []
    },
    {
      "title": "Big Data Revolution",
      "id": "https://www.safaribooksonline.com/api/v1/book/9781118943717/",
      "url": "https://learning.oreilly.com/api/v1/book/9781118943717/",
      "isbn": "9781118943717",
      "format": "book",
      "main_topic": "Data Engineering",
      "secondary_topics": []
    },
    {
      "title": "Designing and Operating a Data Reservoir",
      "id": "https://www.safaribooksonline.com/api/v1/book/0837440663/",
      "url": "https://learning.oreilly.com/api/v1/book/0837440663/",
      "isbn": "9780837440668",
      "format": "book",
      "main_topic": "Data Engineering",
      "secondary_topics": []
    },
    {
      "title": "Finding Profit in Your Organization's Data",
      "id": "https://www.safaribooksonline.com/api/v1/book/9781492042495/",
      "url": "https://learning.oreilly.com/api/v1/book/9781492042495/",
      "isbn": "9781492042495",
      "format": "book",
      "main_topic": "Data Engineering",
      "secondary_topics": []
    },
    {
      "title": "Principles of Data Integration",
      "id": "https://www.safaribooksonline.com/api/v1/book/9780124160446/",
      "url": "https://learning.oreilly.com/api/v1/book/9780124160446/",
      "isbn": "9780123914798",
      "format": "book",
      "main_topic": "Data Engineering",
      "secondary_topics": []
    },
    {
      "title": "Data: Emerging Trends and Technologies",
      "id": "https://www.safaribooksonline.com/api/v1/book/9781492048169/",
      "url": "https://learning.oreilly.com/api/v1/book/9781492048169/",
      "isbn": "9781491920725",
      "format": "book",
      "main_topic": "Data Engineering",
      "secondary_topics": []
    },
    {
      "title": "Big Data Now: 2014 Edition",
      "id": "https://www.safaribooksonline.com/api/v1/book/9781492048091/",
      "url": "https://learning.oreilly.com/api/v1/book/9781492048091/",
      "isbn": "9781491917367",
      "format": "book",
      "main_topic": "Data Engineering",
      "secondary_topics": []
    },
    {
      "title": "Database Design and Relational Theory",
      "id": "https://www.safaribooksonline.com/api/v1/book/9781449330187/",
      "url": "https://learning.oreilly.com/api/v1/book/9781449330187/",
      "isbn": "9781449328016",
      "format": "book",
      "main_topic": "Data Engineering",
      "secondary_topics": []
    },
    {
      "title": "Big Data Application Architecture Q&A: A Problem - Solution Approach",
      "id": "https://www.safaribooksonline.com/api/v1/book/9781430262923/",
      "url": "https://learning.oreilly.com/api/v1/book/9781430262923/",
      "isbn": "9781430262923",
      "format": "book",
      "main_topic": "Data Engineering",
      "secondary_topics": []
    },
    {
      "title": "Principles of Big Data",
      "id": "https://www.safaribooksonline.com/api/v1/book/9780124045767/",
      "url": "https://learning.oreilly.com/api/v1/book/9780124045767/",
      "isbn": "9780124047242",
      "format": "book",
      "main_topic": "Data Engineering",
      "secondary_topics": []
    },
    {
      "title": "Large Scale and Big Data",
      "id": "https://www.safaribooksonline.com/api/v1/book/9781466581500/",
      "url": "https://learning.oreilly.com/api/v1/book/9781466581500/",
      "isbn": "9781466581517",
      "format": "book",
      "main_topic": "Data Engineering",
      "secondary_topics": []
    },
    {
      "title": "Big Data Computing",
      "id": "https://www.safaribooksonline.com/api/v1/book/9781466578388/",
      "url": "https://learning.oreilly.com/api/v1/book/9781466578388/",
      "isbn": "9781466578388",
      "format": "book",
      "main_topic": "Data Engineering",
      "secondary_topics": []
    },
    {
      "title": "The Culture of Big Data",
      "id": "https://www.safaribooksonline.com/api/v1/book/9781491946701/",
      "url": "https://learning.oreilly.com/api/v1/book/9781491946701/",
      "isbn": "9781449367527",
      "format": "book",
      "main_topic": "Data Engineering",
      "secondary_topics": []
    },
    {
      "title": "Disruptive Possibilities: How Big Data Changes Everything",
      "id": "https://www.safaribooksonline.com/api/v1/book/9781449368999/",
      "url": "https://learning.oreilly.com/api/v1/book/9781449368999/",
      "isbn": "9781449369675",
      "format": "book",
      "main_topic": "Data Engineering",
      "secondary_topics": []
    },
    {
      "title": "Information Assurance",
      "id": "https://www.safaribooksonline.com/api/v1/book/9780123735669/",
      "url": "https://learning.oreilly.com/api/v1/book/9780123735669/",
      "isbn": "9780080555881",
      "format": "book",
      "main_topic": "Data Engineering",
      "secondary_topics": []
    },
    {
      "title": "Getting Started with Fluidinfo",
      "id": "https://www.safaribooksonline.com/api/v1/book/9781449331771/",
      "url": "https://learning.oreilly.com/api/v1/book/9781449331771/",
      "isbn": "9781449331795",
      "format": "book",
      "main_topic": "Data Engineering",
      "secondary_topics": []
    },
    {
      "title": "The Data Warehouse ETL Toolkit: Practical Techniques for Extracting, Cleaning, Conforming, and Delivering Data",
      "id": "https://www.safaribooksonline.com/api/v1/book/9780764567575/",
      "url": "https://learning.oreilly.com/api/v1/book/9780764567575/",
      "isbn": "9780764567575",
      "format": "book",
      "main_topic": "Data Engineering",
      "secondary_topics": []
    },
    {
      "title": "Planning for Big Data",
      "id": "https://www.safaribooksonline.com/api/v1/book/9781449333348/",
      "url": "https://learning.oreilly.com/api/v1/book/9781449333348/",
      "isbn": "9781449329648",
      "format": "book",
      "main_topic": "Data Engineering",
      "secondary_topics": []
    },
    {
      "title": "Database Archiving",
      "id": "https://www.safaribooksonline.com/api/v1/book/9780123747204/",
      "url": "https://learning.oreilly.com/api/v1/book/9780123747204/",
      "isbn": "9780080884424",
      "format": "book",
      "main_topic": "Data Engineering",
      "secondary_topics": []
    },
    {
      "title": "Joe Celko's Data, Measurements and Standards in SQL",
      "id": "https://www.safaribooksonline.com/api/v1/book/9780123747228/",
      "url": "https://learning.oreilly.com/api/v1/book/9780123747228/",
      "isbn": "9780080884455",
      "format": "book",
      "main_topic": "Data Engineering",
      "secondary_topics": []
    },
    {
      "title": "Beautiful Data",
      "id": "https://www.safaribooksonline.com/api/v1/book/9780596801656/",
      "url": "https://learning.oreilly.com/api/v1/book/9780596801656/",
      "isbn": "9780596157111",
      "format": "book",
      "main_topic": "Data Engineering",
      "secondary_topics": []
    },
    {
      "title": "Inescapable Data: Harnessing the Power of Convergence",
      "id": "https://www.safaribooksonline.com/api/v1/book/0131852159/",
      "url": "https://learning.oreilly.com/api/v1/book/0131852159/",
      "isbn": "9780131852150",
      "format": "book",
      "main_topic": "Data Engineering",
      "secondary_topics": []
    },
    {
      "title": "Beginning InfoPath™ 2003",
      "id": "https://www.safaribooksonline.com/api/v1/book/9780764579486/",
      "url": "https://learning.oreilly.com/api/v1/book/9780764579486/",
      "isbn": "9780764579486",
      "format": "book",
      "main_topic": "Data Engineering",
      "secondary_topics": []
    },
    {
      "title": "Transactional Information Systems",
      "id": "https://www.safaribooksonline.com/api/v1/book/9781558605084/",
      "url": "https://learning.oreilly.com/api/v1/book/9781558605084/",
      "isbn": "9780080519562",
      "format": "book",
      "main_topic": "Data Engineering",
      "secondary_topics": []
    }
  ]
}